pyhistory/__init__.py
pyhistory/cli.py
pyhistory/exceptions.py
pyhistory/file_config.py
pyhistory/pyhistory.py
pyhistory/utilities.py
pyhistory-2.3.0.dist-info/METADATA
pyhistory-2.3.0.dist-info/WHEEL
pyhistory-2.3.0.dist-info/entry_points.txt
pyhistory-2.3.0.dist-info/licenses/LICENSE
pyhistory-2.3.0.dist-info/RECORD
